github2pypi/__init__.py
github2pypi/replace_url.py
kalman_estimation/__init__.py
kalman_estimation/estimator.py
kalman_estimation/regression.py
kalman_estimation/selector.py
kalman_estimation/tools.py
kalman_estimation/utils.py
kalman_estimation-0.6.0.dist-info/METADATA
kalman_estimation-0.6.0.dist-info/RECORD
kalman_estimation-0.6.0.dist-info/WHEEL
kalman_estimation-0.6.0.dist-info/top_level.txt
