Metadata-Version: 2.1
Name: kalman-estimation
Version: 0.6.0
Summary: Kalman filter based coefficient estimation toolbox.
Home-page: https://github.com/AutuanLiu/Kalman-Filter
Author: Autuan Liu
Author-email: autuanliu@163.com
License: MIT
Platform: UNKNOWN
Classifier: Development Status :: 5 - Production/Stable
Classifier: Intended Audience :: Developers
Classifier: Natural Language :: English
Classifier: Programming Language :: Python
Classifier: Programming Language :: Python :: 3.5
Classifier: Programming Language :: Python :: 3.6
Classifier: Programming Language :: Python :: 3.7
Classifier: Programming Language :: Python :: Implementation :: CPython
Classifier: Programming Language :: Python :: Implementation :: PyPy
Requires-Python: >=3.5
Requires-Dist: numpy
Requires-Dist: matplotlib
Requires-Dist: filterpy
Requires-Dist: scipy
Requires-Dist: scikit-learn
Requires-Dist: yapf
Requires-Dist: torch (>=1.0)
